main/__init__.py
main/cli.py
main/templates/Dockerfile.j2
main/templates/config.yaml.j2
main/templates/docker-compose.yaml.j2
main/templates/env.j2
main/templates/gitignore.j2
main/templates/main.py.j2
main/templates/requirements.txt.j2
main/templates/values.yaml.j2
main/utilities/__init__.py
main/utilities/test.py
main/utilities/typings.py
main/utilities/utils.py
allora_wkr-0.1.34.dist-info/LICENSE
allora_wkr-0.1.34.dist-info/METADATA
allora_wkr-0.1.34.dist-info/WHEEL
allora_wkr-0.1.34.dist-info/entry_points.txt
allora_wkr-0.1.34.dist-info/top_level.txt
allora_wkr-0.1.34.dist-info/RECORD
