Metadata-Version: 2.1
Name: allora-wkr
Version: 0.1.34
Summary: A CLI tool for creating Allora Chain Worker Nodes
Home-page: UNKNOWN
Author: Upshot Technologies
Author-email: tobi@upshot.xyz
License: UNKNOWN
Platform: UNKNOWN
Classifier: Programming Language :: Python :: 3
Classifier: License :: OSI Approved :: MIT License
Classifier: Operating System :: OS Independent
Requires-Python: >=3.7
Requires-Dist: click
Requires-Dist: docker
Requires-Dist: pyyaml
Requires-Dist: jinja2
Requires-Dist: PyYAML
Requires-Dist: termcolor
